md_to_word_mcp/__init__.py
md_to_word_mcp/__main__.py
md_to_word_mcp/converter.py
md_to_word_mcp/server.py
md_to_word_mcp/template_manager.py
md_to_word_mcp/utils.py
md_to_word_mcp-0.1.1.dist-info/METADATA
md_to_word_mcp-0.1.1.dist-info/WHEEL
md_to_word_mcp-0.1.1.dist-info/entry_points.txt
md_to_word_mcp-0.1.1.dist-info/top_level.txt
md_to_word_mcp-0.1.1.dist-info/RECORD
