Metadata-Version: 2.4
Name: md-to-word-mcp
Version: 0.1.1
Summary: 基于MCP协议的Markdown转Word转换工具
Author-email: Assistant <assistant@example.com>
License: MIT
Project-URL: Homepage, https://github.com/example/md-to-word-mcp
Project-URL: Repository, https://github.com/example/md-to-word-mcp
Project-URL: Issues, https://github.com/example/md-to-word-mcp/issues
Classifier: Development Status :: 3 - Alpha
Classifier: Intended Audience :: Developers
Classifier: License :: OSI Approved :: MIT License
Classifier: Programming Language :: Python :: 3
Classifier: Programming Language :: Python :: 3.8
Classifier: Programming Language :: Python :: 3.9
Classifier: Programming Language :: Python :: 3.10
Classifier: Programming Language :: Python :: 3.11
Classifier: Programming Language :: Python :: 3.12
Requires-Python: >=3.10
Requires-Dist: mcp>=0.1.0
Requires-Dist: pypandoc-binary>=1.11
Provides-Extra: dev
Requires-Dist: pytest>=7.0.0; extra == "dev"
Requires-Dist: pytest-asyncio>=0.21.0; extra == "dev"
Requires-Dist: black>=23.0.0; extra == "dev"
Requires-Dist: ruff>=0.1.0; extra == "dev"
Requires-Dist: mypy>=1.0.0; extra == "dev"
